Metadata-Version: 1.1
Name: eepro
Version: 0.1.2
Summary: Arduino based EEPROM Programmer for parallel EEPROMS
Home-page: https://github.com/dangrie158/EEPROgraMmer
Author: Daniel Grießhaber
Author-email: dangrie158@gmail.com
License: MIT
Platform: UNKNOWN
Classifier: Development Status :: 1 - Planning
Classifier: Topic :: Utilities
Classifier: License :: OSI Approved :: MIT License
